{"is_source_file": true, "format": "JavaScript (React component)", "description": "React component for rendering a Tic Tac Toe game board, consisting of a 3x3 grid of squares. It manages rendering individual squares with highlighting for winning lines.", "external_files": ["./Square"], "external_methods": ["React"], "published": ["Board"], "classes": [], "methods": [{"name": "Board({ squares, onClick, winningLine })", "description": "React functional component that renders a 3x3 grid of Square components, highlighting the winning line if provided.", "scope": "", "scopeKind": ""}, {"name": "renderSquare", "description": "Helper function to render individual Square components with appropriate props."}], "calls": ["onClick(i)", "React.createElement", "./Square"], "search-terms": ["Board", "React component", "Tic Tac Toe grid", "Square", "highlight winning line", "renderSquare"], "state": 2, "file_id": 14, "knowledge_revision": 34, "git_revision": "", "ctags": [{"_type": "tag", "name": "Board", "path": "/home/kavia/workspace/code-generation/tic-tac-toe-online-213137-215173/tic_tac_toe_frontend/src/components/Board.js", "pattern": "/^export default function Board({ squares, onClick, winningLine }) {$/", "language": "JavaScript", "kind": "function", "signature": "({ squares, onClick, winningLine })"}, {"_type": "tag", "name": "i", "path": "/home/kavia/workspace/code-generation/tic-tac-toe-online-213137-215173/tic_tac_toe_frontend/src/components/Board.js", "pattern": "/^        key={i}$/", "language": "JavaScript", "kind": "field", "scope": "Board.key", "scopeKind": "class"}, {"_type": "tag", "name": "isWin", "path": "/home/kavia/workspace/code-generation/tic-tac-toe-online-213137-215173/tic_tac_toe_frontend/src/components/Board.js", "pattern": "/^        highlight={isWin}$/", "language": "JavaScript", "kind": "field", "scope": "Board.highlight", "scopeKind": "class"}, {"_type": "tag", "name": "squares", "path": "/home/kavia/workspace/code-generation/tic-tac-toe-online-213137-215173/tic_tac_toe_frontend/src/components/Board.js", "pattern": "/^        value={squares[i]}$/", "language": "JavaScript", "kind": "field", "scope": "Board.value", "scopeKind": "class"}], "hash": "53d97cc7bbaf2c2ddd0c2b47787f720b", "format-version": 4, "code-base-name": "tic_tac_toe_frontend", "filename": "tic_tac_toe_frontend/src/components/Board.js", "fields": [{"name": "key={i}", "scope": "Board.key", "scopeKind": "class", "description": "unavailable"}, {"name": "highlight={isWin}", "scope": "Board.highlight", "scopeKind": "class", "description": "unavailable"}, {"name": "value={squares[i]}", "scope": "Board.value", "scopeKind": "class", "description": "unavailable"}], "revision_history": [{"34": ""}]}